Metadata-Version: 1.0
Name: foxpy
Version: 1.0.0
Summary: Python bindings for FOX - Federated Knowledge Extraction Framework.
Home-page: http://pypi.python.org/pypi/foxpy/
Author: Ivan Ermilov
Author-email: earthquakesan@gmail.com
License: LICENSE.txt
Platform: UNKNOWN
